project.ini
bin/__init__.py
bin/bachelor_start.py
libs/__init__.py
libs/constants.py
libs/containers.py
libs/cli/__init__.py
libs/cli/cli_adapter.py
libs/cli/cli_args.py
libs/common/__init__.py
libs/common/array_extensions.py
libs/common/file_data.py
libs/common/file_data_path.py
libs/common/string_to_bool.py
libs/common/tag_data.py
libs/common/timeit.py
libs/common/hashing/__init__.py
libs/common/hashing/base_hash.py
libs/common/hashing/crc32.py
libs/common/hashing/sha256.py
libs/common/hashing/sha512.py
libs/environment_variables/__init__.py
libs/environment_variables/parsed.py
libs/exceptions/__init__.py
libs/exceptions/base_error.py
libs/exceptions/tack_permission_error.py
libs/exceptions/tack_repository_not_found_error.py
libs/helpers/__init__.py
libs/helpers/read_version.py
libs/plugin/__init__.py
libs/plugin/base_plugin.py
libs/plugin/loader.py
libs/reporting/__init__.py
libs/reporting/json_repository.py
libs/reporting/service.py
libs/reporting/stdout_repository.py
libs/storage/__init__.py
libs/storage/repository_hub.py
libs/storage/service.py
libs/storage/sqlite3_repository.py
libs/storage/migrations/__init__.py
libs/storage/migrations/run_migrations_if_needed.py
libs/storage/migrations/files/__init__.py
libs/storage/migrations/files/migration_1608223240_initial.py
libs/storage/migrations/files/migration_1608223241_after.py
libs/storage/migrations/files/migration_1608223242_drop_description.py
libs/storage/models/__init__.py
libs/storage/models/file.py
libs/storage/models/migration.py
libs/storage/models/tag.py
libs/storage/models/tag_type.py
libs/storage/models/tagged_file.py
libs/suggestions/__init__.py
libs/suggestions/file_path_repository.py
libs/suggestions/service.py
libs/suggestions/suggest_mp3_repository.py
libs/tack_meta/__init__.py
libs/tack_meta/service.py
libs/tack_meta/toml_repository.py
libs/tag_operations/__init__.py
libs/tag_operations/filesystem_repository.py
libs/tag_operations/service.py
libs/usecases/__init__.py
tack_cli-0.1.3.dist-info/LICENSE
tack_cli-0.1.3.dist-info/METADATA
tack_cli-0.1.3.dist-info/WHEEL
tack_cli-0.1.3.dist-info/entry_points.txt
tack_cli-0.1.3.dist-info/top_level.txt
tack_cli-0.1.3.dist-info/RECORD
